twittersentiment/TwitterSentiment.py
twittersentiment/__init__.py
twittersentiment/utils/__init__.py
twittersentiment/utils/data.py
twittersentiment/utils/model.py
twittersentiment/utils/preprocessing.py
twittersentiment/utils/tokenizer.pickle
twittersentiment-0.0.3.dist-info/LICENSE
twittersentiment-0.0.3.dist-info/METADATA
twittersentiment-0.0.3.dist-info/WHEEL
twittersentiment-0.0.3.dist-info/top_level.txt
twittersentiment-0.0.3.dist-info/RECORD
