Metadata-Version: 2.1
Name: twittersentiment
Version: 0.0.3
Summary: A python package for sentiment analysis written using pytorch framework
Home-page: https://github.com/shahules786/Twitter-Sentiment
Author: Shahul ES
Author-email: shahules786@gmail.com
License: UNKNOWN
Platform: UNKNOWN
Classifier: Programming Language :: Python :: 3
Classifier: License :: OSI Approved :: MIT License
Classifier: Operating System :: OS Independent
Requires-Python: >=3.6
Requires-Dist: torch (==1.5.0)
Requires-Dist: torchtext (==0.5.0)
Requires-Dist: tensorflow (==2.2.0)
Requires-Dist: pandas (==1.1.0)
Requires-Dist: scikit-learn (==0.23.0)
Requires-Dist: numpy (==1.19.0)
Requires-Dist: nltk (==3.5)
